setup.py
mm/__init__.py
mm/test.py
mydemon.egg-info/PKG-INFO
mydemon.egg-info/SOURCES.txt
mydemon.egg-info/dependency_links.txt
mydemon.egg-info/requires.txt
mydemon.egg-info/top_level.txt