Metadata-Version: 1.1
Name: mydemon
Version: 1.0.0
Summary: simon test 
Home-page: http://www.douniu.la
Author: simon
Author-email: admin@douniu.la
License: MIT
Keywords: framework testing
Platform: any
Classifier: Programming Language :: Python
